{
    "version": "0.1.206",
    "architecture": {
        "32bit": {
            "url": "https://github.com/logfire-sh/cli/releases/download/v0.1.206/logfire_windows_386.zip",
            "bin": [
                "logfire.exe"
            ],
            "hash": "d8cee5fd24006610bc326c53d3731fc147c74891dc1c8120ced3d9aaa89ed495"
        },
        "64bit": {
            "url": "https://github.com/logfire-sh/cli/releases/download/v0.1.206/logfire_windows_amd64.zip",
            "bin": [
                "logfire.exe"
            ],
            "hash": "fb97b256e733821e0f43219a36c9e72b807d6821f83561bce75556e5d025170d"
        }
    },
    "homepage": "https://logfire.sh/",
    "description": "Logfire command line interface.",
    "depends": [
        "git"
    ],
    "shortcuts": [
        [
            "logfire.exe",
            "logfire"
        ]
    ]
}