{
    "version": "4.3",
    "architecture": {
        "32bit": {
            "url": "https://github.com/logfire-sh/cli/releases/download/v4.3/logfire_windows_386.zip",
            "bin": [
                "logfire.exe"
            ],
            "hash": "2b4d5bdd3985301a3e8da2da72de7bdcb7b541408bfc8ecdac6926a79521bd3f"
        },
        "64bit": {
            "url": "https://github.com/logfire-sh/cli/releases/download/v4.3/logfire_windows_amd64.zip",
            "bin": [
                "logfire.exe"
            ],
            "hash": "197201cd5e11609fc1beb58d74c3e0d89d0741d53c76380c5b4f2f34498dde00"
        },
        "arm64": {
            "url": "https://github.com/logfire-sh/cli/releases/download/v4.3/logfire_windows_arm64.zip",
            "bin": [
                "logfire.exe"
            ],
            "hash": "8528cbfb653b3e9852fcf1498cc160d78111cfd344194d9a374aaa59193a8d59"
        }
    },
    "homepage": "https://logfire.ai/",
    "description": "Logfire command line interface.",
    "depends": [
        "git"
    ],
    "shortcuts": [
        [
            "logfire.exe",
            "logfire"
        ]
    ]
}