{
    "version": "3.4",
    "architecture": {
        "32bit": {
            "url": "https://github.com/logfire-sh/cli/releases/download/v3.4/logfire_windows_386.zip",
            "bin": [
                "logfire.exe"
            ],
            "hash": "0ea27256f2bc032861ca6a4c53d0206f518ace120051b556e5d6df82e10bd67c"
        },
        "64bit": {
            "url": "https://github.com/logfire-sh/cli/releases/download/v3.4/logfire_windows_amd64.zip",
            "bin": [
                "logfire.exe"
            ],
            "hash": "1de658f837311a225016da4865c4319084293eaf97e845705ebc2ad3273b8897"
        },
        "arm64": {
            "url": "https://github.com/logfire-sh/cli/releases/download/v3.4/logfire_windows_arm64.zip",
            "bin": [
                "logfire.exe"
            ],
            "hash": "aea638e4a8001055a8b9824c92f827c07764a8baf70ca5448db9a0248a2e5427"
        }
    },
    "homepage": "https://logfire.ai/",
    "description": "Logfire command line interface.",
    "depends": [
        "git"
    ],
    "shortcuts": [
        [
            "logfire.exe",
            "logfire"
        ]
    ]
}