{
    "version": "1.1",
    "architecture": {
        "32bit": {
            "url": "https://github.com/logfire-sh/cli/releases/download/v1.1/logfire_windows_386.zip",
            "bin": [
                "logfire.exe"
            ],
            "hash": "8db3c0cb3037df22cb55116ccda984917bb2cb3187355915125c3338786734ce"
        },
        "64bit": {
            "url": "https://github.com/logfire-sh/cli/releases/download/v1.1/logfire_windows_amd64.zip",
            "bin": [
                "logfire.exe"
            ],
            "hash": "384a17fee14fb54ea5cf9612a5675b930d4b321a6c07e6bb63eac96acc1eab66"
        },
        "arm64": {
            "url": "https://github.com/logfire-sh/cli/releases/download/v1.1/logfire_windows_arm64.zip",
            "bin": [
                "logfire.exe"
            ],
            "hash": "7cba6af6255c086dd0e6fdb8cc50f2576a2711d90a6c68e6a98a2e94b7d4e4a4"
        }
    },
    "homepage": "https://logfire.ai/",
    "description": "Logfire command line interface.",
    "depends": [
        "git"
    ],
    "shortcuts": [
        [
            "logfire.exe",
            "logfire"
        ]
    ]
}