{
    "version": "4.3",
    "architecture": {
        "32bit": {
            "url": "https://github.com/logfire-sh/cli/releases/download/v4.3/logfire_windows_386.zip",
            "bin": [
                "logfire.exe"
            ],
            "hash": "3e8c4880668aa3bf02a70c8847e3604abea1ed9e42ce06e720e06b442d17b180"
        },
        "64bit": {
            "url": "https://github.com/logfire-sh/cli/releases/download/v4.3/logfire_windows_amd64.zip",
            "bin": [
                "logfire.exe"
            ],
            "hash": "1373ef82e0643770e616ec22aeb41681ac1e76313f234ec1dd92c0b9b19a43bb"
        },
        "arm64": {
            "url": "https://github.com/logfire-sh/cli/releases/download/v4.3/logfire_windows_arm64.zip",
            "bin": [
                "logfire.exe"
            ],
            "hash": "a5a3c8ee0bec54b15f39f6bf196b918ce375f1411e7031050ba65ed19532a498"
        }
    },
    "homepage": "https://logfire.ai/",
    "description": "Logfire command line interface.",
    "depends": [
        "git"
    ],
    "shortcuts": [
        [
            "logfire.exe",
            "logfire"
        ]
    ]
}