{
    "version": "5.8",
    "architecture": {
        "32bit": {
            "url": "https://github.com/logfire-sh/cli/releases/download/v5.8/logfire_windows_386.zip",
            "bin": [
                "logfire.exe"
            ],
            "hash": "7e08da65ae12dc383b511ca775087cb0316cc0ab330ad47499737ff31022187f"
        },
        "64bit": {
            "url": "https://github.com/logfire-sh/cli/releases/download/v5.8/logfire_windows_amd64.zip",
            "bin": [
                "logfire.exe"
            ],
            "hash": "42b1cf8f8e58c5b2f5420196fa710fe043fc3236b6b7671bdc54800444137591"
        },
        "arm64": {
            "url": "https://github.com/logfire-sh/cli/releases/download/v5.8/logfire_windows_arm64.zip",
            "bin": [
                "logfire.exe"
            ],
            "hash": "742dade8872b324c100e0ba8b0332fb88cc537d1abafeeb43e164bc016d357b2"
        }
    },
    "homepage": "https://logfire.ai/",
    "description": "Logfire command line interface.",
    "depends": [
        "git"
    ],
    "shortcuts": [
        [
            "logfire.exe",
            "logfire"
        ]
    ]
}